happiness/__init__.py
happiness-1.2.0.dist-info/LICENSE
happiness-1.2.0.dist-info/METADATA
happiness-1.2.0.dist-info/WHEEL
happiness-1.2.0.dist-info/top_level.txt
happiness-1.2.0.dist-info/RECORD
